lantern_sl/__init__.py
lantern_sl/config/__init__.py
lantern_sl/config/settings.py
lantern_sl/controllers/__init__.py
lantern_sl/controllers/cognito_controller.py
lantern_sl/controllers/dynamo_controller.py
lantern_sl/controllers/fileupload_controller.py
lantern_sl/serverless/__init__.py
lantern_sl/serverless/base.py
lantern_sl/serverless/crud.py
lantern_sl/utils/__init__.py
lantern_sl/utils/binary_parser.py
lantern_sl/utils/dynamo.py
lantern_sl/utils/event.py
lantern_sl/utils/json.py
lantern_sl/utils/logger.py
lantern_sl/utils/monitor.py
lantern_sl/utils/request.py
lantern_sl/utils/time.py
tests/controllers/__init__.py
tests/controllers/test_dynamo_controller.py
tests/utils/__init__.py
tests/utils/test_dynamo.py
tests/utils/test_json.py
tests/utils/test_json_payload.py
tests/utils/test_request.py
tests/utils/test_request_payload.py
tests/utils/test_time.py
lantern_sl-1.1.31.dist-info/METADATA
lantern_sl-1.1.31.dist-info/WHEEL
lantern_sl-1.1.31.dist-info/top_level.txt
lantern_sl-1.1.31.dist-info/RECORD
