Metadata-Version: 2.1
Name: lantern-sl
Version: 1.1.31
Summary: Lantern Serverless Tools
Home-page: https://gitlab.com/lantern-tech/lantern-sl.git
Author: Lantern Technologies
Author-email: support@lantern.tech
License: BSD
Platform: any
Classifier: Development Status :: 5 - Production/Stable
Classifier: Environment :: Console
Classifier: Intended Audience :: Developers
Classifier: License :: OSI Approved :: BSD License
Classifier: Operating System :: POSIX
Classifier: Operating System :: MacOS
Classifier: Operating System :: Unix
Classifier: Operating System :: Microsoft :: Windows
Classifier: Programming Language :: Python :: 3
Classifier: Topic :: Software Development :: Libraries :: Python Modules
Requires-Dist: marshmallow (==3.2.2)
Requires-Dist: pytz (>=2020.1)
Requires-Dist: lantern-data-manager (>=1.0.23)
